{
  "*": {
    "*": {
      "*": {
        "*": {
          "*": ""
        }
      }
    }
  },
  "service-trls": {
    "retrieve": {
      "*": {
        "*": {
          "*": "*"
        }
      }
    },
    "list": {
      "*": {
        "*": {
          "*": "*"
        }
      }
    },
    "create": {
      "*": {
        "*": {
          "*": "*"
        }
      }
    },
    "update": {
      "*": {
        "*": {
          "*": "*"
        }
      }
    },
    "delete": {
      "*": {
        "*": {
          "*": "*"
        }
      }
    }
  },
  "users": {
    "retrieve": {
      "*": {
        "*": {
          "*": "*"
        }
      }
    },
    "list": {
      "*": {
        "*": {
          "*": "*"
        }
      }
    },
    "create": {
      "*": {
        "*": {
          "*": "*"
        }
      }
    },
    "update": {
      "*": {
        "*": {
          "*": "*"
        }
      }
    },
    "delete": {
      "*": {
        "*": {
          "*": "*"
        }
      }
    }
  }
}
